Metadata-Version: 2.1
Name: tap-helpscout
Version: 1.2.0
Summary: Singer.io tap for extracting data from the HelpScout Mailbox API 2.0
Home-page: UNKNOWN
Author: jeff.huth@bytecode.io
License: UNKNOWN
Platform: UNKNOWN
Classifier: Programming Language :: Python :: 3 :: Only
Provides-Extra: dev
